accord/__init__.py
accord/meta.py
accord/option/__init__.py
accord/option/__init__.pyi
accord/option/interface.py
accord/option/some.py
accord/result/__init__.py
accord/result/__init__.pyi
accord/result/err.py
accord/result/interface.py
accord/result/ok.py
accord_types-0.1.0b3.dist-info/licenses/LICENSE
accord_types-0.1.0b3.dist-info/METADATA
accord_types-0.1.0b3.dist-info/WHEEL
accord_types-0.1.0b3.dist-info/top_level.txt
accord_types-0.1.0b3.dist-info/RECORD
