Metadata-Version: 2.4
Name: accord-types
Version: 0.1.0b3
Summary: Agnostic-language library to use Result and Option from Rust
Author-email: Carlos Manso <carlosmgov7k@gmail.com>
License:                                  Apache License
Classifier: Programming Language :: Python :: 3
Classifier: License :: OSI Approved :: Apache Software License
Classifier: Operating System :: OS Independent
Requires-Python: >=3.7
License-File: LICENSE
Dynamic: license-file
